[
  {
    "title": "Sembark Travel Agency Software Overview: Features, Benefits, Pricing and Installation & Training",
    "date": "18 Jun, 2021",
    "author": "Rajat Sharma",
    "description": "Get latest insights into the Sembark Travel Management Software which can supercharge your travel business to grow further.",
    "url": "/blogs/overview-features-benefits-pricing-and-installation-with-training/"
  },
  {
    "title": "How to make sure On-Time Payments from your customers",
    "date": "02 Nov, 2020",
    "author": "Rajat Sharma",
    "description": "Ensuring timely payments from customers is a real challenge for a Travel business. Not getting timely payments from customers can choke off cash flow and can be really frustrating for any business.",
    "url": "/blogs/how-to-make-sure-on-time-payment-from-your-customers/"
  }
]
